uule_grabber/__init__.py
uule_grabber/uule_grabber.py
uule_grabber-0.1.9.dist-info/LICENSE
uule_grabber-0.1.9.dist-info/METADATA
uule_grabber-0.1.9.dist-info/WHEEL
uule_grabber-0.1.9.dist-info/top_level.txt
uule_grabber-0.1.9.dist-info/RECORD
